Workbook

Sheet Assumptions
A1: TELESALES — FINANCIAL MODEL ASSUMPTIONS
A3: REVENUE
A4: Mix tier Starter (%) | B4: 0.3
A5: Mix tier Pro Hybrid (%) | B5: 0.6
A6: Mix tier Premium (%) | B6: 0.1
A7: Prezzo Starter €/mese | B7: 1490
A8: Prezzo Pro Hybrid €/mese | B8: 3290
A9: Prezzo Premium €/mese (blended con variable) | B9: 10000
A10: ARPU blended €/anno | B10: =SUMPRODUCT(B3:B5,B6:B8)*12
A11: Base customers (giu 2026) | B11: 12
A12: Net new customers/mese Y1 | B12: 2.5
A13: Net new customers/mese Y2 | B13: 5
A14: Net new customers/mese Y3 | B14: 4
A15: Churn annuo % | B15: 0.18
A16: NRR — Net Revenue Retention | B16: 1.05
A17: COSTS
A18: Gross margin % Y1 | B18: 0.45
A19: Gross margin % Y2 | B19: 0.51
A20: Gross margin % Y3 | B20: 0.55
A21: CAC blended Y1 (€) | B21: 2000
A22: CAC blended Y2 (€) | B22: 1700
A23: CAC blended Y3 (€) | B23: 1500
A24: OpEx Y1 (€) | B24: 400000
A25: OpEx Y2 (€) | B25: 560000
A26: OpEx Y3 (€) | B26: 740000
A27: Tax rate effective | B27: 0.26

Sheet Unit Economics
A1: UNIT ECONOMICS — per cliente blended
A2: Metric | B2: Y1 | C2: Y2 | D2: Y3
A3: ARPU blended €/anno | B3: =Assumptions!B9 | C3: =Assumptions!B9 | D3: =Assumptions!B9
A4: Gross margin % | B4: =Assumptions!B17 | C4: =Assumptions!B18 | D4: =Assumptions!B19
A5: Gross profit per customer € | B5: =B3*B4 | C5: =C3*C4 | D5: =D3*D4
A6: CAC blended € | B6: =Assumptions!B20 | C6: =Assumptions!B21 | D6: =Assumptions!B22
A7: Retention media (anni) | B7: =1/Assumptions!B15 | C7: =1/Assumptions!B15 | D7: =1/Assumptions!B15
A8: LTV (no NRR) € | B8: =B3*B4*B7 | C8: =C3*C4*C7 | D8: =D3*D4*D7
A9: NRR-adjusted multiplier | B9: =1/(1-(Assumptions!B16-1)) | C9: =1/(1-(Assumptions!B16-1)) | D9: =1/(1-(Assumptions!B16-1))
A10: LTV (with NRR) € | B10: =B8*B9 | C10: =C8*C9 | D10: =D8*D9
A11: LTV:CAC ratio | B11: =B10/B6 | C11: =C10/C6 | D11: =D10/D6
A12: CAC payback (mesi) | B12: =B6/(B3/12*B4) | C12: =C6/(C3/12*C4) | D12: =D6/(D3/12*D4)

Sheet P&L 3y
A1: PROFIT & LOSS — 3 anni base case
A2: Voce € | B2: Y1 (Q4 2026) | C2: Y2 (Q4 2027) | D2: Y3 (Q4 2028)
A3: Total customers fine periodo | B3: =Assumptions!B10+Assumptions!B11*12-(Assumptions!B10+Assumptions!B11*6)*Assumptions!B15 | C3: =B3+Assumptions!B12*12-(B3+Assumptions!B12*6)*Assumptions!B15 | D3: =C3+Assumptions!B13*12-(C3+Assumptions!B13*6)*Assumptions!B15
A4: Revenue (ARR run-rate) € | B4: =B3*Assumptions!B9 | C4: =C3*Assumptions!B9 | D4: =D3*Assumptions!B9
A5: Gross margin % | B5: =Assumptions!B17 | C5: =Assumptions!B18 | D5: =Assumptions!B19
A6: Gross profit € | B6: =B4*B5 | C6: =C4*C5 | D6: =D4*D5
A7: Marketing & sales € | B7: -200000 | C7: -280000 | D7: -350000
A8: R&D / product € | B8: -60000 | C8: -100000 | D8: -140000
A9: G&A € | B9: -140000 | C9: -180000 | D9: -250000
A10: Total OpEx € | B10: =SUM(B7:B9) | C10: =SUM(C7:C9) | D10: =SUM(D7:D9)
A11: EBITDA € | B11: =B6+B10 | C11: =C6+C10 | D11: =D6+D10
A12: EBITDA % | B12: =B11/B4 | C12: =C11/C4 | D12: =D11/D4
A13: Tax (su EBITDA positivo) € | B13: =IF(B11>0,-B11*Assumptions!B24,0) | C13: =IF(C11>0,-C11*Assumptions!B24,0) | D13: =IF(D11>0,-D11*Assumptions!B24,0)
A14: Net Income € | B14: =B11+B13 | C14: =C11+C13 | D14: =D11+D13
A15: Net Income margin % | B15: =B14/B4 | C15: =C14/C4 | D15: =D14/D4

Sheet Sensitivity
A1: SENSITIVITY ANALYSIS — 3 scenari
A2: Variabile | B2: Conservative | C2: Base | D2: Optimistic
A3: Net new customers/mese Y1 | B3: 1.5 | C3: 2.5 | D3: 4
A4: ARPU blended € | B4: 30000 | C4: 36252 | D4: 45000
A5: Churn annuo % | B5: 0.22 | C5: 0.18 | D5: 0.13
A6: CAC blended € | B6: 2500 | C6: 2000 | D6: 1700
A7: Gross margin % | B7: 0.4 | C7: 0.45 | D7: 0.55
A9: OUTCOMES Y1
A10: Customers Y1 (Q4 2026) | B10: =12+B3*12-12*B5 | C10: =12+C3*12-12*C5 | D10: =12+D3*12-12*D5
A11: ARR Y1 € | B11: =B10*B4 | C11: =C10*C4 | D11: =D10*D4
A12: Gross profit Y1 € | B12: =B11*B7 | C12: =C11*C7 | D12: =D11*D7
A13: OPEX Y1 € | B13: 400000 | C13: 400000 | D13: 400000
A14: EBITDA Y1 € | B14: =B12-B13 | C14: =C12-C13 | D14: =D12-D13
A15: EBITDA % Y1 | B15: =B14/B11 | C15: =C14/C11 | D15: =D14/D11
A17: OUTCOMES Y3
A18: Customers Y3 € | B18: =B10+(B3+1)*24-(B10+B3*12)*B5*2 | C18: =C10+(C3+1)*24-(C10+C3*12)*C5*2 | D18: =D10+(D3+1)*24-(D10+D3*12)*D5*2
A19: ARR Y3 € | B19: =B17*B4 | C19: =C17*C4 | D19: =D17*D4
