Workbook

Sheet Risk Matrix
A1: ID | B1: Categoria | C1: Risk | D1: Probability (1-5) | E1: Impact (1-5) | F1: Score (P×I) | G1: Early warning indicators | H1: Mitigation strategy | I1: Contingency plan | J1: Owner | K1: Status
A2: R1 | B2: Market | C2: Commoditization piattaforme Voice AI (Vapi/Synthflow italianizzano UX) | D2: 4 | E2: 4 | F2: =D2*E2 | G2: Brand-leadership + vertical depth + KB proprietaria | H2: Pivot a managed service premium + abbandono fascia low | I2: Founder | J2: Active
A3: R2 | B3: Market | C3: Recession economica EU/IT 2026-2027 | D3: 3 | E3: 3 | F3: =D3*E3 | G3: Diversificazione clienti + pricing flex + cash reserve 6m | H3: Freeze hiring + sconti retention -20% | I3: Founder | J3: Monitor
A4: R3 | B4: Market | C4: Sierra/Parloa/NICE scendono a PMI | D4: 2 | E4: 4 | F4: =D4*E4 | G4: Customer loyalty + casi studio PMI prima 2028 | H4: Posizionarsi come Parloa partner / M&A friendly | I4: Founder | J4: Monitor
A5: R4 | B5: Operational | C5: Dipendenza tecnica da ElevenLabs (single supplier) | D5: 3 | E5: 4 | F5: =D5*E5 | G5: Multi-vendor stack: Cartesia + Deepgram + contratto enterprise | H5: Switch a Cartesia per nuovi clienti in 30 gg | I5: Tech lead | J5: Active
A6: R5 | B6: Operational | C6: Founder bandwidth saturato / key person dependency | D6: 4 | E6: 3 | F6: =D6*E6 | G6: Hire marketing mgr giu 2026 + AE Q1 2027 + docs Notion | H6: Setter senior promosso interim COO | I6: Founder | J6: Critical
A7: R6 | B7: Operational | C7: Setter umano turnover (Karima/Barbara) | D7: 3 | E7: 3 | F7: =D7*E7 | G7: Bonus + career path + backup setter | H7: Redistribuzione 2 sett + hire urgente ex-BPO | I7: HR | J7: Monitor
A8: R7 | B8: Financial | C8: Cash flow stress da onboarding lungo / pagamento ritardato | D8: 3 | E8: 3 | F8: =D8*E8 | G8: Stripe automation + annuali upfront + linea credito €100-200k | H8: Rallentare hiring 1 trimestre; new logo upfront only | I8: CFO/Founder | J8: Monitor
A9: R8 | B9: Financial | C9: CAC blended esplode (>€3.000) | D9: 3 | E9: 4 | F9: =D9*E9 | G9: Diversificare canali; 35% referral; content marketing | H9: Shift budget verso referral; rivedere ICP tight | I9: Marketing mgr | J9: Active
A10: R9 | B10: Financial | C10: Currency rischi (USD up vs EUR) | D10: 2 | E10: 2 | F10: =D10*E10 | G10: Hedging valutario se >€100k esposizione/anno; preferire vendor EU | H10: Pass-through pricing cliente con clausola FX | I10: CFO | J10: Monitor
A11: R10 | B11: Regulatory | C11: AI Act Art. 50 non-compliance al 2 ago 2026 | D11: 5 | E11: 4 | F11: =D11*E11 | G11: Disclosure vocale entro 15 lug 2026 + DPA + consulente | H11: Pausa servizio AI Voice automatizzato fino a compliance | I11: Founder + DPA | J11: Critical
A12: R11 | B12: Regulatory | C12: Sanzione Garante per cliente B2C riattivazione (filiera) | D12: 2 | E12: 5 | F12: =D12*E12 | G12: Lead provenance audit obbligatorio + clausola indennità + DPA audit right | H12: Separazione legal entity B2C; insurance D&O | I12: Founder + DPA | J12: Active
A13: R12 | B13: Regulatory | C13: Class action consumatori contro Telesales o filiera | D13: 2 | E13: 4 | F13: =D13*E13 | G13: Compliance-first + due diligence cliente + insurance | H13: Insurance €1-3M coverage; legal hold | I13: Founder | J13: Monitor
... A16: R15 | B16: Reputational | C16: Reputational contagion (associazione cliente B2C controverso) | D16: 3 | E16: 3 | F16: =D16*E16 | G16: Due diligence cliente; separazione brand B2C; PR proattiva | H16: Termination clausola contratto se cliente in litigation | I16: Founder | J16: Monitor

Sheet Summary
A1: Risk Summary by Category
A3: Categoria | B3: # risk | C3: Score totale | D3: Score medio
A4: Market | B4: =COUNTIF('Risk Matrix'!B:B,"Market") | C4: =SUMIF('Risk Matrix'!B:B,"Market",'Risk Matrix'!F:F) | D4: =IFERROR(C4/B4,0)
A5: Operational | B5: =COUNTIF('Risk Matrix'!B:B,"Operational") | C5: =SUMIF('Risk Matrix'!B:B,"Operational",'Risk Matrix'!F:F) | D5: =IFERROR(C5/B5,0)
A6: Financial | B6: =COUNTIF('Risk Matrix'!B:B,"Financial") | C6: =SUMIF('Risk Matrix'!B:B,"Financial",'Risk Matrix'!F:F) | D6: =IFERROR(C6/B6,0)
A7: Regulatory | B7: =COUNTIF('Risk Matrix'!B:B,"Regulatory") | C7: =SUMIF('Risk Matrix'!B:B,"Regulatory",'Risk Matrix'!F:F) | D7: =IFERROR(C7/B7,0)
A8: Reputational | B8: =COUNTIF('Risk Matrix'!B:B,"Reputational") | C8: =SUMIF('Risk Matrix'!B:B,"Reputational",'Risk Matrix'!F:F) | D8: =IFERROR(C8/B8,0)
A10: TOTALE | B10: =SUM(B4:B8) | C10: =SUM(C4:C8) | D10: =IFERROR(C10/B10,0)
A12: Risk Score legend (P × I)
A13: 15-25 (Critical) | B13: Azione immediata richiesta
A14: 10-14 (Active) | B14: Mitigation attiva continua
A15: 7-9 (Monitor) | B15: Monitorare trimestralmente
A16: 1-6 (Accept) | B16: Rischio accettabile
